[
    {
        "id": 1,
        "title": "25/7 support",
        "text": "Lorem, ipsum dolor sit amet consectetur adipisicing elit. Lorem, ipsum dolor sit amet consectetur adipisicing elit. "
    },
    {
        "id": 2,
        "title": "25/7 support",
        "text": "Lorem, ipsum dolor sit amet consectetur adipisicing elit. Lorem, ipsum dolor sit amet consectetur adipisicing elit. "
    },
    {
        "id": 3,
        "title": "25/7 support",
        "text": "Lorem, ipsum dolor sit amet consectetur adipisicing elit. Lorem, ipsum dolor sit amet consectetur adipisicing elit. "
    },
    {
        "id": 4,
        "title": "25/7 support",
        "text": "Lorem, ipsum dolor sit amet consectetur adipisicing elit. Lorem, ipsum dolor sit amet consectetur adipisicing elit. "
    }
]